{"trial_id": "0", "hyperparameters": {"space": [{"class_name": "Int", "config": {"name": "units", "default": null, "conditions": [], "min_value": 8, "max_value": 128, "step": 8, "sampling": "linear"}}, {"class_name": "Choice", "config": {"name": "optimizer", "default": "adam", "conditions": [], "values": ["adam", "sgd", "rmsprop", "adadelta"], "ordered": false}}], "values": {"units": 48, "optimizer": "sgd"}}, "metrics": {"metrics": {"accuracy": {"direction": "max", "observations": [{"value": [0.732899010181427], "step": 9}]}, "loss": {"direction": "min", "observations": [{"value": [0.5585397481918335], "step": 9}]}, "val_accuracy": {"direction": "max", "observations": [{"value": [0.7337662577629089], "step": 9}]}, "val_loss": {"direction": "min", "observations": [{"value": [0.5712600350379944], "step": 9}]}}}, "score": 0.7337662577629089, "best_step": 9, "status": "COMPLETED", "message": null}